[
  {
    "id": 2069484512984371663,
    "text": "First Southwest Airlines flight with Starlink! https://t.co/JBK7fE0r91",
    "summary": "First Southwest Airlines flight with Starlink!",
    "created_at": "Jun 23, 06:15 PM UTC",
    "url": "https://x.com/elonmusk/status/2069484512984371663",
    "retweets": 8012,
    "likes": 116813,
    "replies": 2837,
    "impressions": 12504389,
    "score": 146523,
    "virality": "\ud83d\udd25 Viral",
    "parent": null,
    "ai_summary": "Southwest Airlines completed its first flight equipped with Starlink satellite internet connectivity, demonstrating a significant commercial application of SpaceX's Starlink constellation beyond traditional ground-based internet. This milestone represents both a business partnership validating Starlink's in-flight connectivity product and a competitive advancement in the commercial aviation market, where inflight internet has become a key passenger amenity.",
    "is_relevant": true,
    "embed_html": "<blockquote class=\"twitter-tweet\" data-width=\"550\" data-dnt=\"true\" data-theme=\"dark\"><p lang=\"en\" dir=\"ltr\">First Southwest Airlines flight with Starlink! <a href=\"https://t.co/JBK7fE0r91\">https://t.co/JBK7fE0r91</a></p>&mdash; Elon Musk (@elonmusk) <a href=\"https://x.com/elonmusk/status/2069484512984371663?ref_src=twsrc%5Etfw\">June 23, 2026</a></blockquote>\n\n"
  },
  {
    "id": 2069535601892987275,
    "text": "Starlink coming to @AmericanAir next year! https://t.co/JsLEfZq7AD",
    "summary": "Starlink coming to @AmericanAir next year!",
    "created_at": "Jun 23, 09:38 PM UTC",
    "url": "https://x.com/elonmusk/status/2069535601892987275",
    "retweets": 5819,
    "likes": 63599,
    "replies": 2706,
    "impressions": 11324615,
    "score": 86468,
    "virality": "\ud83d\udd25 Viral",
    "parent": null,
    "ai_summary": "Elon Musk announced that Starlink satellite internet service will be integrated into American Airlines' in-flight connectivity offering starting next year. This represents a significant B2B expansion for Starlink beyond consumer markets, demonstrating how the company is commercializing its satellite infrastructure for enterprise partnerships and improving customer experience in aviation\u2014a key business development milestone for scaling Starlink's revenue streams.",
    "is_relevant": true,
    "embed_html": "<blockquote class=\"twitter-tweet\" data-width=\"550\" data-dnt=\"true\" data-theme=\"dark\"><p lang=\"en\" dir=\"ltr\">Starlink coming to <a href=\"https://x.com/AmericanAir?ref_src=twsrc%5Etfw\">@AmericanAir</a> next year! <a href=\"https://t.co/JsLEfZq7AD\">https://t.co/JsLEfZq7AD</a></p>&mdash; Elon Musk (@elonmusk) <a href=\"https://x.com/elonmusk/status/2069535601892987275?ref_src=twsrc%5Etfw\">June 23, 2026</a></blockquote>\n\n"
  }
]